numula/MidiFile.py
numula/__init__.py
numula/notate.py
numula/notate_nuance.py
numula/notate_score.py
numula/nscore.py
numula/nuance.py
numula/pianoteq.py
numula/poly_pan.py
numula/read_midifile.py
numula/spatialize.py
numula/temp
numula/vol_name.py
numula-1.0.0.dist-info/METADATA
numula-1.0.0.dist-info/WHEEL
numula-1.0.0.dist-info/entry_points.txt
numula-1.0.0.dist-info/license_files/LICENSE
numula-1.0.0.dist-info/RECORD
