Metadata-Version: 2.1
Name: numula
Version: 1.0.0
Summary: A Python library for creating nuanced music with MIDI.
Project-URL: Bug Tracker, https://github.com/davidpanderson/Numula/issues
Project-URL: Homepage, https://github.com/davidpanderson/Numula
Author-email: "David P. Anderson" <davea@berkeley.edu>
Classifier: License :: OSI Approved :: GNU Lesser General Public License v3 (LGPLv3)
Classifier: Operating System :: OS Independent
Classifier: Programming Language :: Python :: 3
Requires-Python: >=3.0
